qtlets/__init__.py
qtlets/qtlets.py
qtlets/widgets.py
qtlets-0.4.dist-info/licenses/LICENSE
qtlets-0.4.dist-info/METADATA
qtlets-0.4.dist-info/WHEEL
qtlets-0.4.dist-info/top_level.txt
qtlets-0.4.dist-info/RECORD
