Metadata-Version: 2.4
Name: qtlets
Version: 0.4
Summary: Qt with less boilerplate
Author-email: Samuel Palato <7659022+spalato@users.noreply.github.com>
License-Expression: MIT
Project-URL: Homepage, https://github.com/spalato/qtlets
Project-URL: Source, https://github.com/spalato/qtlets
Project-URL: Tracker, https://github.com/spalato/qtlets/issues
Keywords: qt,qtwidgets,pyside6,gui
Classifier: Development Status :: 4 - Beta
Classifier: Intended Audience :: Developers
Classifier: Topic :: Software Development :: Libraries
Classifier: Programming Language :: Python :: 3
Classifier: Programming Language :: Python :: 3 :: Only
Classifier: Programming Language :: Python :: 3.8
Classifier: Programming Language :: Python :: 3.9
Classifier: Programming Language :: Python :: 3.10
Classifier: Programming Language :: Python :: 3.11
Classifier: Operating System :: OS Independent
Requires-Python: >=3.8
License-File: LICENSE
Requires-Dist: PySide6
Provides-Extra: dev
Requires-Dist: pytest; extra == "dev"
Requires-Dist: attrs; extra == "dev"
Requires-Dist: traitlets; extra == "dev"
Dynamic: license-file
